sqlite3_create_and_check_table/__init__.py
sqlite3_create_and_check_table/version.py
sqlite3_create_and_check_table-2024.2.dist-info/METADATA
sqlite3_create_and_check_table-2024.2.dist-info/WHEEL
sqlite3_create_and_check_table-2024.2.dist-info/licenses/LICENSE.txt
sqlite3_create_and_check_table-2024.2.dist-info/RECORD
