Metadata-Version: 2.3
Name: sqlite3-create_and_check_table
Version: 2024.2
Summary: Create an SQLite table if missing or check that the existing table matches the given creation statement.
Project-URL: Homepage, https://gitlab.inria.fr/jrye/sqlite3-create_and_check_table
Project-URL: Source, https://gitlab.inria.fr/jrye/sqlite3-create_and_check_table.git
Project-URL: Documentation, https://jrye.gitlabpages.inria.fr/sqlite3-create_and_check_table
Project-URL: Issues, https://gitlab.inria.fr/jrye/sqlite3-create_and_check_table/-/issues
Author-email: Jan-Michael Rye <jan-michael.rye@inria.fr>
License: MIT License
License-File: LICENSE.txt
Classifier: License :: OSI Approved :: MIT License
Classifier: Operating System :: OS Independent
Classifier: Programming Language :: Python :: 3
Requires-Python: >=3.7
